{
  "source": "assets/derived/walls_clean_edge.png",
  "preprocess": {
    "alpha_threshold": 8,
    "trim_exports": true,
    "padding": 8
  },
  "slices": [
    {
      "name": "wall_vertical_left_end",
      "rect": [30, 3, 90, 674],
      "pivot": [0.5, 0.5],
      "notes": "Top-row first piece; labeled LEFT END in the source sheet."
    },
    {
      "name": "wall_vertical_middle",
      "rect": [254, 4, 91, 675],
      "pivot": [0.5, 0.5],
      "notes": "Top-row second piece; labeled MIDDLE in the source sheet."
    },
    {
      "name": "wall_vertical_plain_a",
      "rect": [460, 3, 92, 676],
      "pivot": [0.5, 0.5],
      "notes": "Top-row third piece; unlabeled vertical variant."
    },
    {
      "name": "wall_vertical_right_end",
      "rect": [682, 2, 92, 678],
      "pivot": [0.5, 0.5],
      "notes": "Top-row fourth piece; labeled RIGHT END in the source sheet."
    },
    {
      "name": "wall_vertical_plain_b",
      "rect": [906, 3, 94, 677],
      "pivot": [0.5, 0.5],
      "notes": "Top-row fifth piece; unlabeled vertical variant with diagonal accent."
    },
    {
      "name": "wall_vertical_bottom_end",
      "rect": [1130, 4, 91, 674],
      "pivot": [0.5, 0.5],
      "notes": "Top-row sixth piece; labeled BOTTOM END in the source sheet."
    },
    {
      "name": "wall_corner_left_end",
      "rect": [36, 731, 176, 172],
      "pivot": [0.5, 0.5],
      "notes": "Bottom-row first piece; labeled LEFTEND in the source sheet."
    },
    {
      "name": "wall_corner_right_end",
      "rect": [293, 731, 163, 172],
      "pivot": [0.5, 0.5],
      "notes": "Bottom-row second piece; labeled RIGHT END in the source sheet."
    },
    {
      "name": "wall_corner_bottom_end",
      "rect": [725, 803, 172, 102],
      "pivot": [0.5, 0.5],
      "notes": "Bottom-row third piece; labeled BOTTOM END in the source sheet."
    },
    {
      "name": "wall_corner_bottom_end_tall",
      "rect": [968, 731, 206, 172],
      "pivot": [0.5, 0.5],
      "notes": "Bottom-row fourth piece; larger bottom-end corner variant."
    }
  ]
}
